{
	"source": "./src",
	"destination": "./docs",
	"excludes": ["commands(\\/|\\\\)[a-z-]+\\1[a-z-]+\\.js$"],
	"plugins": [
		{ "name": "esdoc-es7-plugin" }
	],
	"title": "GRAF",
	"manual": {
		"overview": ["./manual/overview.md"],
		"installation": ["./manual/installation.md"],
		"usage": [
			"./manual/usage-info.md",
			"./manual/usage-first-steps.md",
			"./manual/usage-commands.md",
			"./manual/usage-permissions.md",
			"./manual/usage-storage.md",
			"./manual/usage-util.md"
		],
		"configuration": ["./manual/configuration.md"]
	}
}
