{
  "coverage": "9.09%",
  "expectCount": 77,
  "actualCount": 7,
  "files": {
    "src/errors/command-format.js": {
      "expectCount": 3,
      "actualCount": 0,
      "undocumentLines": [
        7,
        8,
        10
      ]
    },
    "src/errors/friendly.js": {
      "expectCount": 3,
      "actualCount": 0,
      "undocumentLines": [
        4,
        5,
        7
      ]
    },
    "src/database/mod-role.js": {
      "expectCount": 10,
      "actualCount": 0,
      "undocumentLines": [
        7,
        77,
        53,
        35,
        61,
        8,
        18,
        13,
        71,
        9
      ]
    },
    "src/database/setting.js": {
      "expectCount": 13,
      "actualCount": 0,
      "undocumentLines": [
        6,
        7,
        34,
        45,
        60,
        52,
        9,
        14,
        24,
        19,
        11,
        15,
        10
      ]
    },
    "src/database/usable-channel.js": {
      "expectCount": 11,
      "actualCount": 0,
      "undocumentLines": [
        7,
        83,
        53,
        35,
        61,
        8,
        18,
        13,
        77,
        71,
        9
      ]
    },
    "src/util.js": {
      "expectCount": 8,
      "actualCount": 7,
      "undocumentLines": [
        19
      ]
    },
    "src/commands/dispatcher.js": {
      "expectCount": 12,
      "actualCount": 0,
      "undocumentLines": [
        16,
        19,
        105,
        197,
        172,
        67,
        128,
        116,
        14,
        15,
        154,
        139
      ]
    },
    "src/commands/registry.js": {
      "expectCount": 6,
      "actualCount": 0,
      "undocumentLines": [
        6,
        34,
        7,
        50,
        28,
        10
      ]
    },
    "src/config.js": {
      "expectCount": 5,
      "actualCount": 0,
      "undocumentLines": [
        7,
        37,
        27,
        23,
        4
      ]
    },
    "src/index.js": {
      "expectCount": 3,
      "actualCount": 0,
      "undocumentLines": [
        36,
        33,
        34
      ]
    },
    "src/permissions.js": {
      "expectCount": 2,
      "actualCount": 0,
      "undocumentLines": [
        17,
        8
      ]
    },
    "src/version.js": {
      "expectCount": 1,
      "actualCount": 0,
      "undocumentLines": [
        7
      ]
    }
  }
}